lsspy/__init__.py
lsspy/__main__.py
lsspy/cli.py
lsspy/models.py
lsspy/py.typed
lsspy/server.py
lsspy/watcher.py
lsspy/readers/__init__.py
lsspy/readers/runtime.py
lsspy/readers/spec.py
lsspy/static/index.html
lsspy_cli-0.3.0.dist-info/METADATA
lsspy_cli-0.3.0.dist-info/WHEEL
lsspy_cli-0.3.0.dist-info/entry_points.txt
lsspy_cli-0.3.0.dist-info/licenses/LICENSE
lsspy_cli-0.3.0.dist-info/RECORD
