Metadata-Version: 2.4
Name: lsspy-cli
Version: 0.3.0
Summary: Real-time visualization dashboard for Lodestar-managed repositories
Project-URL: Homepage, https://github.com/ThomasRohde/lsspy
Project-URL: Repository, https://github.com/ThomasRohde/lsspy
Project-URL: Issues, https://github.com/ThomasRohde/lsspy/issues
Project-URL: Documentation, https://github.com/ThomasRohde/lsspy#readme
Project-URL: Changelog, https://github.com/ThomasRohde/lsspy/blob/main/CHANGELOG.md
Author: Lodestar Team
License: MIT License
License-File: LICENSE
Keywords: agent-coordination,dashboard,lodestar,monitoring,real-time,task-management,visualization,websocket
Classifier: Development Status :: 3 - Alpha
Classifier: Framework :: FastAPI
Classifier: Intended Audience :: Developers
Classifier: License :: OSI Approved :: MIT License
Classifier: Operating System :: OS Independent
Classifier: Programming Language :: Python :: 3
Classifier: Programming Language :: Python :: 3 :: Only
Classifier: Programming Language :: Python :: 3.12
Classifier: Topic :: Software Development :: Libraries
Classifier: Topic :: Software Development :: Libraries :: Python Modules
Classifier: Topic :: System :: Monitoring
Classifier: Typing :: Typed
Requires-Python: >=3.12
Requires-Dist: fastapi>=0.115.0
Requires-Dist: pydantic>=2.9.0
Requires-Dist: pyyaml>=6.0.2
Requires-Dist: rich>=13.9.0
Requires-Dist: typer>=0.12.0
Requires-Dist: uvicorn[standard]>=0.32.0
Requires-Dist: watchdog>=5.0.0
Provides-Extra: dev
Requires-Dist: httpx>=0.27.0; extra == 'dev'
Requires-Dist: mypy>=1.13.0; extra == 'dev'
Requires-Dist: pytest-asyncio>=0.24.0; extra == 'dev'
Requires-Dist: pytest>=8.0.0; extra == 'dev'
Requires-Dist: ruff>=0.7.0; extra == 'dev'
